vizent/__init__.py
vizent/background_image.py
vizent/background_map.py
vizent/glyph_shapes.py
vizent/legend_utils.py
vizent/metofficelimits.py
vizent/scales.py
vizent/vizent_plot.py
vizent/images/423562.png
vizent/images/423563.png
vizent/images/423564.png
vizent/images/423565.png
vizent/images/424562.png
vizent/images/424563.png
vizent/images/424564.png
vizent/images/424565.png
vizent/images/425562.png
vizent/images/425563.png
vizent/images/425564.png
vizent/images/425565.png
vizent/images/426562.png
vizent/images/426563.png
vizent/images/426564.png
vizent/images/426565.png
vizent/images/all.png
vizent/images/england_map.png
vizent/images/no_map.png
vizent/tests/test_background_image.py
vizent/tests/test_background_map.py
vizent/tests/test_plotting.py
vizent/tests/test_scales.py
vizent/tests/test_shapes.py
vizent-1.1.2.dist-info/LICENSE.txt
vizent-1.1.2.dist-info/METADATA
vizent-1.1.2.dist-info/WHEEL
vizent-1.1.2.dist-info/top_level.txt
vizent-1.1.2.dist-info/RECORD
