Metadata-Version: 2.1
Name: vizent
Version: 1.1.2
Summary: A python library for visualising bivariate data using glyphs and node-link diagrams with matplotlib.
Author-email: Peter Baudains <peter.baudains@kcl.ac.uk>, Lucy McLaughlin <lucy.mclaughlin@ncl.ac.uk>
License: Copyright 2021 CUSP London, Lucy McLaughlin
Keywords: visualization,plot,bivariate,glyphs,scatterplot,dataviz,networks,uncertainty
Classifier: Development Status :: 4 - Beta
Classifier: Intended Audience :: End Users/Desktop
Classifier: Intended Audience :: Science/Research
Classifier: Topic :: Scientific/Engineering :: Visualization
Classifier: License :: OSI Approved :: MIT License
Classifier: Programming Language :: Python :: 3
License-File: LICENSE.txt
Requires-Dist: matplotlib
Requires-Dist: numpy
Requires-Dist: scipy
Provides-Extra: background_image
Requires-Dist: pillow ; extra == 'background_image'
Provides-Extra: background_map
Requires-Dist: cartopy ; extra == 'background_map'
